babel.py
babel_compiler-0.0.0.dev0.dist-info/LICENSE
babel_compiler-0.0.0.dev0.dist-info/METADATA
babel_compiler-0.0.0.dev0.dist-info/WHEEL
babel_compiler-0.0.0.dev0.dist-info/top_level.txt
babel_compiler-0.0.0.dev0.dist-info/zip-safe
babel_compiler-0.0.0.dev0.dist-info/RECORD
