Metadata-Version: 2.1
Name: babel-compiler
Version: 0.0.0.dev0
Summary: The compiler for next generation Python.
Home-page: https://github.com/JarryShaw/babel
Author: Jarry Shaw
Author-email: jarryshaw@icloud.com
License: MIT License
Keywords: back-port compiler
Platform: UNKNOWN
Classifier: Development Status :: 1 - Planning
Classifier: Intended Audience :: Developers
Classifier: License :: OSI Approved :: MIT License
Classifier: Natural Language :: English
Classifier: Operating System :: OS Independent
Classifier: Programming Language :: Python
Classifier: Topic :: Software Development
Classifier: Topic :: Utilities
